video_converter_3d/__init__.py
video_converter_3d/converter.py
3d_video_converter-0.0.4.dist-info/LICENSE
3d_video_converter-0.0.4.dist-info/METADATA
3d_video_converter-0.0.4.dist-info/WHEEL
3d_video_converter-0.0.4.dist-info/top_level.txt
3d_video_converter-0.0.4.dist-info/RECORD
