Metadata-Version: 2.1
Name: 3d-video-converter
Version: 0.0.4
Summary: FFMPEG-based tool for converting either two separate stereo videos or an existing 3D video into a wide range of 3D video formats.
Home-page: https://github.com/evoth/3d-video-converter
Author: Ethan Voth
Author-email: ethanvoth7@gmail.com
Classifier: Programming Language :: Python :: 3
Classifier: License :: OSI Approved :: MIT License
Classifier: Operating System :: OS Independent
License-File: LICENSE
Requires-Dist: ffmpeg-python
Requires-Dist: opencv-python
